b15py/__init__.py
b15py/b15f.py
b15py/channels.py
b15py/commands.py
b15py/ports.py
b15py/registers.py
b15py/utilities.py
b15py-1.0.4.dist-info/METADATA
b15py-1.0.4.dist-info/WHEEL
b15py-1.0.4.dist-info/top_level.txt
b15py-1.0.4.dist-info/RECORD
